AUTHORS
LICENSE
MANIFEST.in
README.rst
README.txt
epydoc.conf
setup.cfg
setup.py
eeml/__init__.py
eeml/datastream.py
eeml/invalidator.py
eeml/namespace.py
eeml/unit.py
eeml/util.py
eeml/validator.py
eeml/validators.py
python_eeml.egg-info/PKG-INFO
python_eeml.egg-info/SOURCES.txt
python_eeml.egg-info/dependency_links.txt
python_eeml.egg-info/not-zip-safe
python_eeml.egg-info/requires.txt
python_eeml.egg-info/top_level.txt