Metadata-Version: 1.1
Name: python-eeml
Version: 4.1.0
Summary: Python support for the Extended Environments Markup Language
Home-page: https://github.com/petervizi/python-eeml
Author: Peter Vizi
Author-email: peter.vizi@gmail.com
License: GPLv3
Download-URL: https://github.com/petervizi/python-eeml/zipball/4.1.0
Keywords: eeml,environment,xml,pachube,cosm
Platform: UNKNOWN
Classifier: Development Status :: 3 - Alpha
Classifier: Topic :: Software Development :: Libraries :: Python Modules
Classifier: Intended Audience :: Developers
Classifier: Operating System :: OS Independent
Classifier: Programming Language :: Python
